web/db/dbapi.py
web/db/me.py
web/db/release.py
web/db/sa.py
web/db/util.py
web/db/__pycache__/dbapi.cpython-37.opt-1.pyc
web/db/__pycache__/me.cpython-37.opt-1.pyc
web/db/__pycache__/release.cpython-37.opt-1.pyc
web/db/__pycache__/sa.cpython-37.opt-1.pyc
web/db/__pycache__/util.cpython-37.opt-1.pyc
web/ext/db.py
web/ext/__pycache__/db.cpython-37.opt-1.pyc
web.db-3.0.0.dist-info/LICENSE.txt
web.db-3.0.0.dist-info/METADATA
web.db-3.0.0.dist-info/WHEEL
web.db-3.0.0.dist-info/entry_points.txt
web.db-3.0.0.dist-info/top_level.txt
web.db-3.0.0.dist-info/RECORD
