Metadata-Version: 2.1
Name: web.db
Version: 3.0.0
Summary: General database adapter layer for common configuration and operation.
Home-page: https://github.com/marrow/web.db
Author: Alice Bevan-McGregor
Author-email: alice@gothcandy.com
License: MIT
Download-URL: https://github.com/marrow/web.db/releases
Project-URL: Repository, https://github.com/marrow/web.db/
Project-URL: Documentation, https://github.com/marrow/web.db/#readme
Project-URL: Issue Tracker, https://github.com/marrow/web.db/issues
Project-URL: Funding, https://www.patreon.com/GothAlice
Keywords: marrow,web.ext,web.db,WebCore,database connector
Platform: UNKNOWN
Classifier: Development Status :: 5 - Production/Stable
Classifier: Environment :: Console
Classifier: Environment :: Web Environment
Classifier: Intended Audience :: Developers
Classifier: License :: OSI Approved :: MIT License
Classifier: Operating System :: OS Independent
Classifier: Programming Language :: Python
Classifier: Programming Language :: Python :: 3
Classifier: Programming Language :: Python :: 3.6
Classifier: Programming Language :: Python :: 3.7
Classifier: Programming Language :: Python :: 3.8
Classifier: Programming Language :: Python :: Implementation :: CPython
Classifier: Programming Language :: Python :: Implementation :: PyPy
Classifier: Topic :: Software Development :: Libraries
Classifier: Topic :: Software Development :: Libraries :: Python Modules
Requires-Dist: marrow.package (~=2.0.0)
Requires-Dist: WebCore (~=3.0.0)
Provides-Extra: development
Requires-Dist: pytest ; extra == 'development'
Requires-Dist: pytest-cov ; extra == 'development'
Requires-Dist: pytest-flakes ; extra == 'development'
Requires-Dist: pymongo ; extra == 'development'
Requires-Dist: mongoengine ; extra == 'development'
Requires-Dist: sqlalchemy ; extra == 'development'
Requires-Dist: pre-commit ; extra == 'development'
